[{"id": "802", "player_name": "Diego Costa", "games": "28", "time": "2386", "goals": "12", "xG": "12.080561252310872", "assists": "6", "xA": "2.8887829119339585", "shots": "68", "key_passes": "30", "yellow_cards": "8", "red_cards": "0", "position": "F S", "team_title": "Chelsea", "npg": "12", "npxG": "12.080561252310872", "xGChain": "18.07464148849249", "xGBuildup": "5.290680217556655"}, {"id": "687", "player_name": "Pedro", "games": "29", "time": "2061", "goals": "7", "xG": "6.120481324382126", "assists": "2", "xA": "4.614513913169503", "shots": "57", "key_passes": "42", "yellow_cards": "3", "red_cards": "0", "position": "M S", "team_title": "Chelsea", "npg": "7", "npxG": "6.120481324382126", "xGChain": "16.050377681851387", "xGBuildup": "6.954227411188185"}, {"id": "686", "player_name": "Cesc F\u00e0bregas", "games": "37", "time": "2901", "goals": "5", "xG": "3.869542864151299", "assists": "7", "xA": "8.421024333685637", "shots": "45", "key_passes": "67", "yellow_cards": "5", "red_cards": "0", "position": "M S", "team_title": "Chelsea", "npg": "3", "npxG": "2.347205144353211", "xGChain": "19.53799346741289", "xGBuildup": "14.364742730744183"}, {"id": "700", "player_name": "Willian", "games": "35", "time": "2766", "goals": "5", "xG": "4.4275355488061905", "assists": "6", "xA": "7.687527693808079", "shots": "60", "key_passes": "81", "yellow_cards": "5", "red_cards": "0", "position": "M S", "team_title": "Chelsea", "npg": "5", "npxG": "4.4275355488061905", "xGChain": "13.175751902163029", "xGBuildup": "6.594237174838781"}, {"id": "701", "player_name": "Eden Hazard", "games": "31", "time": "2183", "goals": "4", "xG": "2.578371874988079", "assists": "3", "xA": "4.175006851553917", "shots": "36", "key_passes": "66", "yellow_cards": "2", "red_cards": "0", "position": "F M S", "team_title": "Chelsea", "npg": "4", "npxG": "2.578371874988079", "xGChain": "11.917042413726449", "xGBuildup": "8.38061559945345"}, {"id": "692", "player_name": "Oscar", "games": "27", "time": "1785", "goals": "3", "xG": "5.171860884875059", "assists": "3", "xA": "3.2977483849972486", "shots": "52", "key_passes": "29", "yellow_cards": "4", "red_cards": "0", "position": "M S", "team_title": "Chelsea", "npg": "2", "npxG": "3.6495231799781322", "xGChain": "10.23574398085475", "xGBuildup": "5.516653552651405"}, {"id": "681", "player_name": "C\u00e9sar Azpilicueta", "games": "37", "time": "3208", "goals": "2", "xG": "1.2036293791607022", "assists": "3", "xA": "2.2325293626636267", "shots": "10", "key_passes": "21", "yellow_cards": "7", "red_cards": "0", "position": "D S", "team_title": "Chelsea", "npg": "2", "npxG": "1.2036293791607022", "xGChain": "12.767135987058282", "xGBuildup": "11.378272647038102"}, {"id": "682", "player_name": "Branislav Ivanovic", "games": "33", "time": "2922", "goals": "2", "xG": "2.355594513937831", "assists": "2", "xA": "2.006993959657848", "shots": "28", "key_passes": "13", "yellow_cards": "5", "red_cards": "0", "position": "D", "team_title": "Chelsea", "npg": "2", "npxG": "2.355594513937831", "xGChain": "10.849223083816469", "xGBuildup": "9.198493051342666"}, {"id": "695", "player_name": "Bertrand Traor\u00e9", "games": "10", "time": "365", "goals": "2", "xG": "1.6593618504703045", "assists": "1", "xA": "0.6275983182713389", "shots": "17", "key_passes": "5", "yellow_cards": "0", "red_cards": "0", "position": "F M S", "team_title": "Chelsea", "npg": "2", "npxG": "1.6593618504703045", "xGChain": "2.3423975370824337", "xGBuildup": "0.15087248757481575"}, {"id": "697", "player_name": "Nemanja Matic", "games": "33", "time": "2426", "goals": "2", "xG": "2.5063633238896728", "assists": "2", "xA": "2.0589730199426413", "shots": "34", "key_passes": "19", "yellow_cards": "4", "red_cards": "1", "position": "M S", "team_title": "Chelsea", "npg": "2", "npxG": "2.5063633238896728", "xGChain": "11.280711317434907", "xGBuildup": "9.022076165303588"}, {"id": "699", "player_name": "Gary Cahill", "games": "23", "time": "1952", "goals": "2", "xG": "1.5026729321107268", "assists": "1", "xA": "0.19687475450336933", "shots": "13", "key_passes": "3", "yellow_cards": "2", "red_cards": "0", "position": "D S", "team_title": "Chelsea", "npg": "2", "npxG": "1.5026729321107268", "xGChain": "1.9389915894716978", "xGBuildup": "1.7717100661247969"}, {"id": "936", "player_name": "Ramires", "games": "12", "time": "612", "goals": "2", "xG": "1.3262335881590843", "assists": "0", "xA": "0.05816144123673439", "shots": "10", "key_passes": "1", "yellow_cards": "1", "red_cards": "0", "position": "M S", "team_title": "Chelsea", "npg": "2", "npxG": "1.3262335881590843", "xGChain": "1.8094926942139864", "xGBuildup": "0.8054327834397554"}, {"id": "688", "player_name": "Ruben Loftus-Cheek", "games": "13", "time": "399", "goals": "1", "xG": "0.9546094238758087", "assists": "0", "xA": "0.13750671222805977", "shots": "12", "key_passes": "4", "yellow_cards": "0", "red_cards": "0", "position": "M S", "team_title": "Chelsea", "npg": "1", "npxG": "0.9546094238758087", "xGChain": "2.5983768925070763", "xGBuildup": "1.7522746697068214"}, {"id": "689", "player_name": "Kenedy", "games": "14", "time": "544", "goals": "1", "xG": "0.3206859976053238", "assists": "0", "xA": "0.5036234222352505", "shots": "13", "key_passes": "6", "yellow_cards": "0", "red_cards": "0", "position": "D M S", "team_title": "Chelsea", "npg": "1", "npxG": "0.3206859976053238", "xGChain": "2.955372128635645", "xGBuildup": "2.2893560379743576"}, {"id": "690", "player_name": "Lo\u00efc Remy", "games": "13", "time": "269", "goals": "1", "xG": "2.083794981241226", "assists": "0", "xA": "0.15876663196831942", "shots": "13", "key_passes": "4", "yellow_cards": "0", "red_cards": "0", "position": "F S", "team_title": "Chelsea", "npg": "1", "npxG": "2.083794981241226", "xGChain": "2.4009386422112584", "xGBuildup": "0.158377006649971"}, {"id": "691", "player_name": "Alexandre Pato", "games": "2", "time": "134", "goals": "1", "xG": "1.720166027545929", "assists": "0", "xA": "0", "shots": "4", "key_passes": "0", "yellow_cards": "0", "red_cards": "0", "position": "F S", "team_title": "Chelsea", "npg": "0", "npxG": "0.9589971788227558", "xGChain": "1.6412881016731262", "xGBuildup": "0.6822909116744995"}, {"id": "696", "player_name": "Falcao", "games": "10", "time": "208", "goals": "1", "xG": "0.7739494685083628", "assists": "0", "xA": "0.09176904708147049", "shots": "11", "key_passes": "2", "yellow_cards": "1", "red_cards": "0", "position": "F S", "team_title": "Chelsea", "npg": "1", "npxG": "0.7739494685083628", "xGChain": "0.8805259186774492", "xGBuildup": "0.19261372834444046"}, {"id": "917", "player_name": "John Terry", "games": "24", "time": "1999", "goals": "1", "xG": "1.4788393825292587", "assists": "0", "xA": "0.10227394197136164", "shots": "10", "key_passes": "2", "yellow_cards": "2", "red_cards": "2", "position": "D", "team_title": "Chelsea", "npg": "1", "npxG": "1.4788393825292587", "xGChain": "4.600792312994599", "xGBuildup": "3.987738722935319"}, {"id": "935", "player_name": "Kurt Zouma", "games": "23", "time": "1912", "goals": "1", "xG": "1.8363511050119996", "assists": "1", "xA": "0.5467774271965027", "shots": "17", "key_passes": "1", "yellow_cards": "0", "red_cards": "0", "position": "D S", "team_title": "Chelsea", "npg": "1", "npxG": "1.8363511050119996", "xGChain": "3.94202867615968", "xGBuildup": "3.8601794838905334"}, {"id": "680", "player_name": "Thibaut Courtois", "games": "23", "time": "2023", "goals": "0", "xG": "0", "assists": "0", "xA": "0", "shots": "0", "key_passes": "0", "yellow_cards": "1", "red_cards": "2", "position": "GK", "team_title": "Chelsea", "npg": "0", "npxG": "0", "xGChain": "3.1832844708114862", "xGBuildup": "3.1832844708114862"}, {"id": "683", "player_name": "Matt Miazga", "games": "2", "time": "138", "goals": "0", "xG": "0", "assists": "0", "xA": "0", "shots": "0", "key_passes": "0", "yellow_cards": "1", "red_cards": "0", "position": "D", "team_title": "Chelsea", "npg": "0", "npxG": "0", "xGChain": "0.2594698369503021", "xGBuildup": "0.2594698369503021"}, {"id": "684", "player_name": "Abdul Rahman Baba", "games": "15", "time": "1018", "goals": "0", "xG": "0.3791148830205202", "assists": "1", "xA": "0.17924091219902039", "shots": "6", "key_passes": "3", "yellow_cards": "1", "red_cards": "0", "position": "D S", "team_title": "Chelsea", "npg": "0", "npxG": "0.3791148830205202", "xGChain": "3.869670283049345", "xGBuildup": "3.490555379539728"}, {"id": "685", "player_name": "John Obi Mikel", "games": "25", "time": "1782", "goals": "0", "xG": "0.2847853694111109", "assists": "1", "xA": "0.109479452483356", "shots": "7", "key_passes": "5", "yellow_cards": "6", "red_cards": "0", "position": "D M S", "team_title": "Chelsea", "npg": "0", "npxG": "0.2847853694111109", "xGChain": "6.554197784513235", "xGBuildup": "6.356603622436523"}, {"id": "693", "player_name": "Jake Clarke-Salter", "games": "1", "time": "13", "goals": "0", "xG": "0", "assists": "0", "xA": "0", "shots": "0", "key_passes": "0", "yellow_cards": "0", "red_cards": "0", "position": "S", "team_title": "Chelsea", "npg": "0", "npxG": "0", "xGChain": "0.14084462821483612", "xGBuildup": "0.14084462821483612"}, {"id": "694", "player_name": "Asmir Begovic", "games": "17", "time": "1393", "goals": "0", "xG": "0", "assists": "0", "xA": "0", "shots": "0", "key_passes": "0", "yellow_cards": "0", "red_cards": "0", "position": "GK S", "team_title": "Chelsea", "npg": "0", "npxG": "0", "xGChain": "1.3994954600930214", "xGBuildup": "1.3994954600930214"}, {"id": "702", "player_name": "Tammy Abraham", "games": "2", "time": "51", "goals": "0", "xG": "0.16510771214962006", "assists": "0", "xA": "0", "shots": "2", "key_passes": "0", "yellow_cards": "0", "red_cards": "0", "position": "S", "team_title": "Chelsea", "npg": "0", "npxG": "0.16510771214962006", "xGChain": "0.16510771214962006", "xGBuildup": "0"}, {"id": "703", "player_name": "Fikayo Tomori", "games": "1", "time": "29", "goals": "0", "xG": "0", "assists": "0", "xA": "0", "shots": "0", "key_passes": "0", "yellow_cards": "0", "red_cards": "0", "position": "S", "team_title": "Chelsea", "npg": "0", "npxG": "0", "xGChain": "0", "xGBuildup": "0"}, {"id": "1089", "player_name": "Juan Cuadrado", "games": "1", "time": "22", "goals": "0", "xG": "0.03935323283076286", "assists": "0", "xA": "0", "shots": "1", "key_passes": "0", "yellow_cards": "0", "red_cards": "0", "position": "S", "team_title": "Chelsea", "npg": "0", "npxG": "0.03935323283076286", "xGChain": "0.03935323283076286", "xGBuildup": "0"}]