[{"id": "1389", "player_name": "Jorginho", "games": "28", "time": "2022", "goals": "7", "xG": "6.972690678201616", "assists": "1", "xA": "1.954869382083416", "shots": "14", "key_passes": "24", "yellow_cards": "2", "red_cards": "0", "position": "M S", "team_title": "Chelsea", "npg": "0", "npxG": "0.12224532943218946", "xGChain": "11.383730475790799", "xGBuildup": "10.87897537369281"}, {"id": "65", "player_name": "Timo Werner", "games": "35", "time": "2605", "goals": "6", "xG": "13.432795586064458", "assists": "8", "xA": "6.66727664321661", "shots": "80", "key_passes": "36", "yellow_cards": "2", "red_cards": "0", "position": "F M S", "team_title": "Chelsea", "npg": "6", "npxG": "13.432795586064458", "xGChain": "20.533462934195995", "xGBuildup": "5.242121719755232"}, {"id": "702", "player_name": "Tammy Abraham", "games": "22", "time": "1027", "goals": "6", "xG": "6.189150683581829", "assists": "1", "xA": "0.7214874606579542", "shots": "32", "key_passes": "9", "yellow_cards": "0", "red_cards": "0", "position": "F S", "team_title": "Chelsea", "npg": "6", "npxG": "6.189150683581829", "xGChain": "7.9011704083532095", "xGBuildup": "2.1223282255232334"}, {"id": "7768", "player_name": "Mason Mount", "games": "36", "time": "2891", "goals": "6", "xG": "6.884880336001515", "assists": "5", "xA": "9.847691355273128", "shots": "82", "key_passes": "87", "yellow_cards": "2", "red_cards": "0", "position": "F M S", "team_title": "Chelsea", "npg": "5", "npxG": "6.123711509630084", "xGChain": "21.69607448298484", "xGBuildup": "12.443149040453136"}, {"id": "935", "player_name": "Kurt Zouma", "games": "24", "time": "2024", "goals": "5", "xG": "3.1368534453213215", "assists": "0", "xA": "0.08146697096526623", "shots": "27", "key_passes": "4", "yellow_cards": "3", "red_cards": "0", "position": "D S", "team_title": "Chelsea", "npg": "5", "npxG": "3.1368534453213215", "xGChain": "6.216146335937083", "xGBuildup": "6.133133308030665"}, {"id": "502", "player_name": "Olivier Giroud", "games": "17", "time": "750", "goals": "4", "xG": "5.070415806025267", "assists": "0", "xA": "1.1757991276681423", "shots": "29", "key_passes": "6", "yellow_cards": "1", "red_cards": "0", "position": "F S", "team_title": "Chelsea", "npg": "4", "npxG": "5.070415806025267", "xGChain": "5.245491370558739", "xGBuildup": "1.7113372217863798"}, {"id": "2662", "player_name": "Christian Pulisic", "games": "27", "time": "1739", "goals": "4", "xG": "6.775412477552891", "assists": "2", "xA": "2.7612321693450212", "shots": "43", "key_passes": "25", "yellow_cards": "2", "red_cards": "0", "position": "F M S", "team_title": "Chelsea", "npg": "4", "npxG": "6.775412477552891", "xGChain": "14.593857947736979", "xGBuildup": "7.101119593717158"}, {"id": "5220", "player_name": "Kai Havertz", "games": "27", "time": "1523", "goals": "4", "xG": "6.352183712646365", "assists": "3", "xA": "1.553381915204227", "shots": "33", "key_passes": "18", "yellow_cards": "2", "red_cards": "0", "position": "F M S", "team_title": "Chelsea", "npg": "4", "npxG": "6.352183712646365", "xGChain": "10.382943627424538", "xGBuildup": "4.811911249533296"}, {"id": "782", "player_name": "Ben Chilwell", "games": "27", "time": "2296", "goals": "3", "xG": "2.9848903995007277", "assists": "5", "xA": "2.455677840858698", "shots": "27", "key_passes": "30", "yellow_cards": "3", "red_cards": "0", "position": "D M", "team_title": "Chelsea", "npg": "3", "npxG": "2.9848903995007277", "xGChain": "11.330961346626282", "xGBuildup": "8.155131921172142"}, {"id": "1621", "player_name": "Marcos Alonso", "games": "13", "time": "962", "goals": "2", "xG": "1.8240782842040062", "assists": "0", "xA": "1.7216993779875338", "shots": "22", "key_passes": "15", "yellow_cards": "2", "red_cards": "0", "position": "D S", "team_title": "Chelsea", "npg": "2", "npxG": "1.8240782842040062", "xGChain": "4.643395733088255", "xGBuildup": "2.536423623561859"}, {"id": "3288", "player_name": "Thiago Silva", "games": "23", "time": "1938", "goals": "2", "xG": "1.3205454014241695", "assists": "0", "xA": "0.2914941646158695", "shots": "13", "key_passes": "5", "yellow_cards": "3", "red_cards": "1", "position": "D", "team_title": "Chelsea", "npg": "2", "npxG": "1.3205454014241695", "xGChain": "7.84285775385797", "xGBuildup": "7.636919112876058"}, {"id": "6456", "player_name": "Callum Hudson-Odoi", "games": "23", "time": "1048", "goals": "2", "xG": "1.3696892522275448", "assists": "3", "xA": "3.104141779243946", "shots": "23", "key_passes": "31", "yellow_cards": "0", "red_cards": "0", "position": "D F M S", "team_title": "Chelsea", "npg": "2", "npxG": "1.3696892522275448", "xGChain": "7.824358187615871", "xGBuildup": "5.499199015088379"}, {"id": "8992", "player_name": "Hakim Ziyech", "games": "23", "time": "1182", "goals": "2", "xG": "1.9873138703405857", "assists": "3", "xA": "4.4784491918981075", "shots": "35", "key_passes": "34", "yellow_cards": "3", "red_cards": "0", "position": "F M S", "team_title": "Chelsea", "npg": "2", "npxG": "1.9873138703405857", "xGChain": "7.660671561956406", "xGBuildup": "3.6919242860749364"}, {"id": "681", "player_name": "C\u00e9sar Azpilicueta", "games": "26", "time": "2189", "goals": "1", "xG": "0.5030050054192543", "assists": "2", "xA": "2.5754943350329995", "shots": "11", "key_passes": "27", "yellow_cards": "5", "red_cards": "1", "position": "D S", "team_title": "Chelsea", "npg": "1", "npxG": "0.5030050054192543", "xGChain": "13.989242531359196", "xGBuildup": "12.338820736855268"}, {"id": "1822", "player_name": "Antonio R\u00fcdiger", "games": "19", "time": "1710", "goals": "1", "xG": "1.1399364518001676", "assists": "0", "xA": "0.3058073613792658", "shots": "14", "key_passes": "4", "yellow_cards": "0", "red_cards": "0", "position": "D", "team_title": "Chelsea", "npg": "1", "npxG": "1.1399364518001676", "xGChain": "9.137650460004807", "xGBuildup": "9.044836282730103"}, {"id": "8067", "player_name": "Reece James", "games": "32", "time": "2355", "goals": "1", "xG": "1.5345969907939434", "assists": "2", "xA": "3.6499749002978206", "shots": "35", "key_passes": "42", "yellow_cards": "3", "red_cards": "0", "position": "D M S", "team_title": "Chelsea", "npg": "1", "npxG": "1.5345969907939434", "xGChain": "11.71862213127315", "xGBuildup": "9.588866364210844"}, {"id": "200", "player_name": "Andreas Christensen", "games": "17", "time": "1375", "goals": "0", "xG": "0.12940827198326588", "assists": "0", "xA": "0.250104570761323", "shots": "3", "key_passes": "6", "yellow_cards": "2", "red_cards": "1", "position": "D S", "team_title": "Chelsea", "npg": "0", "npxG": "0.12940827198326588", "xGChain": "7.441710580140352", "xGBuildup": "7.276742447167635"}, {"id": "624", "player_name": "Willy Caballero", "games": "1", "time": "90", "goals": "0", "xG": "0", "assists": "0", "xA": "0", "shots": "0", "key_passes": "0", "yellow_cards": "0", "red_cards": "0", "position": "GK", "team_title": "Chelsea", "npg": "0", "npxG": "0", "xGChain": "0.14356312155723572", "xGBuildup": "0.14356312155723572"}, {"id": "703", "player_name": "Fikayo Tomori", "games": "1", "time": "43", "goals": "0", "xG": "0", "assists": "0", "xA": "0", "shots": "0", "key_passes": "0", "yellow_cards": "0", "red_cards": "0", "position": "S", "team_title": "Chelsea", "npg": "0", "npxG": "0", "xGChain": "0.0727275162935257", "xGBuildup": "0.0727275162935257"}, {"id": "751", "player_name": "N&#039;Golo Kant\u00e9", "games": "30", "time": "2142", "goals": "0", "xG": "0.7004624530673027", "assists": "2", "xA": "1.206712644547224", "shots": "10", "key_passes": "22", "yellow_cards": "7", "red_cards": "0", "position": "M S", "team_title": "Chelsea", "npg": "0", "npxG": "0.7004624530673027", "xGChain": "10.102666012942791", "xGBuildup": "8.441409684717655"}, {"id": "1245", "player_name": "Emerson", "games": "2", "time": "88", "goals": "0", "xG": "0", "assists": "0", "xA": "0", "shots": "0", "key_passes": "0", "yellow_cards": "0", "red_cards": "0", "position": "S", "team_title": "Chelsea", "npg": "0", "npxG": "0", "xGChain": "0", "xGBuildup": "0"}, {"id": "2254", "player_name": "Mateo Kovacic", "games": "27", "time": "1833", "goals": "0", "xG": "0.9314172859303653", "assists": "1", "xA": "1.9152584234252572", "shots": "23", "key_passes": "21", "yellow_cards": "4", "red_cards": "0", "position": "M S", "team_title": "Chelsea", "npg": "0", "npxG": "0.9314172859303653", "xGChain": "14.808724199421704", "xGBuildup": "13.03579165134579"}, {"id": "5061", "player_name": "Kepa", "games": "7", "time": "582", "goals": "0", "xG": "0", "assists": "0", "xA": "0", "shots": "0", "key_passes": "0", "yellow_cards": "1", "red_cards": "0", "position": "GK S", "team_title": "Chelsea", "npg": "0", "npxG": "0", "xGChain": "0.30502439849078655", "xGBuildup": "0.30502439849078655"}, {"id": "6880", "player_name": "Edouard Mendy", "games": "31", "time": "2748", "goals": "0", "xG": "0", "assists": "0", "xA": "0", "shots": "0", "key_passes": "0", "yellow_cards": "2", "red_cards": "0", "position": "GK", "team_title": "Chelsea", "npg": "0", "npxG": "0", "xGChain": "4.780523473396897", "xGBuildup": "4.780523473396897"}, {"id": "7988", "player_name": "Billy Gilmour", "games": "5", "time": "256", "goals": "0", "xG": "0.05113431066274643", "assists": "0", "xA": "0.12365835532546043", "shots": "1", "key_passes": "3", "yellow_cards": "0", "red_cards": "0", "position": "M S", "team_title": "Chelsea", "npg": "0", "npxG": "0.05113431066274643", "xGChain": "0.5436719954013824", "xGBuildup": "0.4064304232597351"}]