[{"id": "498", "player_name": "Alexis S\u00e1nchez", "games": "35", "time": "2967", "goals": "16", "xG": "13.451749975793064", "assists": "8", "xA": "8.49417957291007", "shots": "122", "key_passes": "82", "yellow_cards": "4", "red_cards": "0", "position": "F M S", "team_title": "Arsenal", "npg": "16", "npxG": "12.690581078641117", "xGChain": "27.15757153555751", "xGBuildup": "10.736752955242991"}, {"id": "502", "player_name": "Olivier Giroud", "games": "27", "time": "1871", "goals": "14", "xG": "8.846344472840428", "assists": "3", "xA": "3.8601362351328135", "shots": "70", "key_passes": "29", "yellow_cards": "5", "red_cards": "1", "position": "F S", "team_title": "Arsenal", "npg": "14", "npxG": "8.846344472840428", "xGChain": "13.639880420640111", "xGBuildup": "4.129246938973665"}, {"id": "965", "player_name": "Santiago Cazorla", "games": "37", "time": "2999", "goals": "7", "xG": "10.590722324326634", "assists": "11", "xA": "9.755179909989238", "shots": "93", "key_passes": "78", "yellow_cards": "5", "red_cards": "0", "position": "M S", "team_title": "Arsenal", "npg": "1", "npxG": "6.023709328845143", "xGChain": "24.65783429890871", "xGBuildup": "16.913314290344715"}, {"id": "504", "player_name": "Aaron Ramsey", "games": "29", "time": "2013", "goals": "6", "xG": "6.636925790458918", "assists": "6", "xA": "5.299688201397657", "shots": "63", "key_passes": "47", "yellow_cards": "6", "red_cards": "0", "position": "M S", "team_title": "Arsenal", "npg": "6", "npxG": "6.636925790458918", "xGChain": "16.72075515240431", "xGBuildup": "8.166224788874388"}, {"id": "503", "player_name": "Theo Walcott", "games": "14", "time": "427", "goals": "5", "xG": "5.347009994089603", "assists": "0", "xA": "0.40138599276542664", "shots": "23", "key_passes": "4", "yellow_cards": "0", "red_cards": "0", "position": "F M S", "team_title": "Arsenal", "npg": "5", "npxG": "5.347009994089603", "xGChain": "5.9333066791296005", "xGBuildup": "0.6996185854077339"}, {"id": "499", "player_name": "Mesut \u00d6zil", "games": "22", "time": "1861", "goals": "4", "xG": "3.860026102513075", "assists": "5", "xA": "6.6569958999753", "shots": "29", "key_passes": "69", "yellow_cards": "0", "red_cards": "0", "position": "F M S", "team_title": "Arsenal", "npg": "4", "npxG": "3.860026102513075", "xGChain": "16.416587620973587", "xGBuildup": "9.916828630492091"}, {"id": "494", "player_name": "Laurent Koscielny", "games": "27", "time": "2289", "goals": "3", "xG": "1.274743553251028", "assists": "0", "xA": "0.116488516330719", "shots": "8", "key_passes": "2", "yellow_cards": "4", "red_cards": "0", "position": "D S", "team_title": "Arsenal", "npg": "3", "npxG": "1.274743553251028", "xGChain": "3.6892644492909312", "xGBuildup": "3.6175646809861064"}, {"id": "492", "player_name": "H\u00e9ctor Beller\u00edn", "games": "20", "time": "1564", "goals": "2", "xG": "0.27969358302652836", "assists": "1", "xA": "1.7710436806082726", "shots": "5", "key_passes": "12", "yellow_cards": "5", "red_cards": "0", "position": "D S", "team_title": "Arsenal", "npg": "2", "npxG": "0.27969358302652836", "xGChain": "6.440684627741575", "xGBuildup": "5.210577918216586"}, {"id": "1036", "player_name": "Jack Wilshere", "games": "14", "time": "739", "goals": "2", "xG": "2.4192265793681145", "assists": "1", "xA": "1.4338911147788167", "shots": "18", "key_passes": "16", "yellow_cards": "4", "red_cards": "0", "position": "M S", "team_title": "Arsenal", "npg": "2", "npxG": "2.4192265793681145", "xGChain": "7.234430808573961", "xGBuildup": "4.517602872103453"}, {"id": "4400", "player_name": "Tomas Rosicky", "games": "15", "time": "562", "goals": "2", "xG": "0.969735087826848", "assists": "1", "xA": "1.5375187862664461", "shots": "10", "key_passes": "7", "yellow_cards": "1", "red_cards": "0", "position": "M S", "team_title": "Arsenal", "npg": "2", "npxG": "0.969735087826848", "xGChain": "4.887206275016069", "xGBuildup": "3.2713690754026175"}, {"id": "508", "player_name": "Calum Chambers", "games": "23", "time": "1574", "goals": "1", "xG": "0.8142128176987171", "assists": "1", "xA": "0.8842720529064536", "shots": "7", "key_passes": "11", "yellow_cards": "7", "red_cards": "1", "position": "D M S", "team_title": "Arsenal", "npg": "1", "npxG": "0.8142128176987171", "xGChain": "3.6191983073949814", "xGBuildup": "3.2758472142741084"}, {"id": "895", "player_name": "Mathieu Flamini", "games": "23", "time": "1455", "goals": "1", "xG": "1.0083513157442212", "assists": "1", "xA": "0.18820588011294603", "shots": "7", "key_passes": "5", "yellow_cards": "3", "red_cards": "0", "position": "M S", "team_title": "Arsenal", "npg": "1", "npxG": "1.0083513157442212", "xGChain": "4.853084901347756", "xGBuildup": "3.8635037560015917"}, {"id": "966", "player_name": "Alex Oxlade-Chamberlain", "games": "23", "time": "1497", "goals": "1", "xG": "2.8491112738847733", "assists": "1", "xA": "3.6900964844971895", "shots": "32", "key_passes": "35", "yellow_cards": "4", "red_cards": "0", "position": "M S", "team_title": "Arsenal", "npg": "1", "npxG": "2.8491112738847733", "xGChain": "9.594998601824045", "xGBuildup": "4.923703037202358"}, {"id": "967", "player_name": "Mathieu Debuchy", "games": "10", "time": "811", "goals": "1", "xG": "0.8225507512688637", "assists": "0", "xA": "0.3981873393058777", "shots": "8", "key_passes": "2", "yellow_cards": "2", "red_cards": "0", "position": "D", "team_title": "Arsenal", "npg": "1", "npxG": "0.8225507512688637", "xGChain": "3.0027846209704876", "xGBuildup": "2.8428300134837627"}, {"id": "493", "player_name": "Gabriel", "games": "6", "time": "347", "goals": "0", "xG": "0.04296275973320007", "assists": "1", "xA": "0.027459410950541496", "shots": "2", "key_passes": "1", "yellow_cards": "0", "red_cards": "0", "position": "D S", "team_title": "Arsenal", "npg": "0", "npxG": "0.04296275973320007", "xGChain": "0.8342677801847458", "xGBuildup": "0.8342677801847458"}, {"id": "495", "player_name": "Nacho Monreal", "games": "28", "time": "2308", "goals": "0", "xG": "0.3041377291083336", "assists": "1", "xA": "1.377957472577691", "shots": "4", "key_passes": "12", "yellow_cards": "3", "red_cards": "0", "position": "D S", "team_title": "Arsenal", "npg": "0", "npxG": "0.3041377291083336", "xGChain": "9.0921392403543", "xGBuildup": "8.257979160174727"}, {"id": "497", "player_name": "Francis Coquelin", "games": "22", "time": "1667", "goals": "0", "xG": "0.0836224053055048", "assists": "0", "xA": "0.18764721043407917", "shots": "5", "key_passes": "5", "yellow_cards": "5", "red_cards": "0", "position": "M S", "team_title": "Arsenal", "npg": "0", "npxG": "0.0836224053055048", "xGChain": "6.154336169362068", "xGBuildup": "6.035230997949839"}, {"id": "505", "player_name": "David Ospina", "games": "18", "time": "1620", "goals": "0", "xG": "0", "assists": "0", "xA": "0.04679638519883156", "shots": "0", "key_passes": "2", "yellow_cards": "0", "red_cards": "0", "position": "GK", "team_title": "Arsenal", "npg": "0", "npxG": "0", "xGChain": "2.064858367666602", "xGBuildup": "2.0180619917809963"}, {"id": "506", "player_name": "Joel Campbell", "games": "4", "time": "34", "goals": "0", "xG": "0", "assists": "0", "xA": "0.08552376180887222", "shots": "0", "key_passes": "2", "yellow_cards": "0", "red_cards": "0", "position": "S", "team_title": "Arsenal", "npg": "0", "npxG": "0", "xGChain": "0.15400913543999195", "xGBuildup": "0.13456231355667114"}, {"id": "507", "player_name": "Per Mertesacker", "games": "35", "time": "3150", "goals": "0", "xG": "0.8197583304718137", "assists": "1", "xA": "0.23774676024913788", "shots": "13", "key_passes": "3", "yellow_cards": "2", "red_cards": "0", "position": "D", "team_title": "Arsenal", "npg": "0", "npxG": "0.8197583304718137", "xGChain": "7.7452892903238535", "xGBuildup": "7.591858083382249"}, {"id": "545", "player_name": "Kieran Gibbs", "games": "22", "time": "1657", "goals": "0", "xG": "1.0783992381766438", "assists": "3", "xA": "1.821300501935184", "shots": "12", "key_passes": "15", "yellow_cards": "3", "red_cards": "0", "position": "D S", "team_title": "Arsenal", "npg": "0", "npxG": "1.0783992381766438", "xGChain": "8.999923517927527", "xGBuildup": "7.215291786938906"}, {"id": "970", "player_name": "Mikel Arteta", "games": "7", "time": "451", "goals": "0", "xG": "0.036514182575047016", "assists": "1", "xA": "0.06850946880877018", "shots": "2", "key_passes": "3", "yellow_cards": "1", "red_cards": "0", "position": "M S", "team_title": "Arsenal", "npg": "0", "npxG": "0.036514182575047016", "xGChain": "1.0064920000731945", "xGBuildup": "0.9221100397408009"}, {"id": "1244", "player_name": "Wojciech Szczesny", "games": "17", "time": "1501", "goals": "0", "xG": "0", "assists": "0", "xA": "0", "shots": "0", "key_passes": "0", "yellow_cards": "1", "red_cards": "0", "position": "GK", "team_title": "Arsenal", "npg": "0", "npxG": "0", "xGChain": "1.1442009713500738", "xGBuildup": "1.1442009713500738"}, {"id": "1750", "player_name": "Ainsley Maitland-Niles", "games": "1", "time": "1", "goals": "0", "xG": "0", "assists": "0", "xA": "0", "shots": "0", "key_passes": "0", "yellow_cards": "0", "red_cards": "0", "position": "S", "team_title": "Arsenal", "npg": "0", "npxG": "0", "xGChain": "0", "xGBuildup": "0"}, {"id": "1790", "player_name": "Chuba Akpom", "games": "3", "time": "23", "goals": "0", "xG": "0.5139968991279602", "assists": "0", "xA": "0", "shots": "2", "key_passes": "0", "yellow_cards": "0", "red_cards": "0", "position": "S", "team_title": "Arsenal", "npg": "0", "npxG": "0.5139968991279602", "xGChain": "0.5139968991279602", "xGBuildup": "0"}, {"id": "3871", "player_name": "Lukas Podolski", "games": "7", "time": "83", "goals": "0", "xG": "0.9136217646300793", "assists": "0", "xA": "0.3546023815870285", "shots": "9", "key_passes": "2", "yellow_cards": "0", "red_cards": "0", "position": "S", "team_title": "Arsenal", "npg": "0", "npxG": "0.9136217646300793", "xGChain": "0.5932805873453617", "xGBuildup": "0.11954313889145851"}, {"id": "4401", "player_name": "Emiliano Martinez", "games": "4", "time": "299", "goals": "0", "xG": "0", "assists": "0", "xA": "0", "shots": "0", "key_passes": "0", "yellow_cards": "0", "red_cards": "0", "position": "GK S", "team_title": "Arsenal", "npg": "0", "npxG": "0", "xGChain": "0.41308738104999065", "xGBuildup": "0.41308738104999065"}]