[{"id": "65", "player_name": "Timo Werner", "games": "34", "time": "2825", "goals": "28", "xG": "23.448496147990227", "assists": "8", "xA": "9.675973629578948", "shots": "123", "key_passes": "53", "yellow_cards": "4", "red_cards": "0", "position": "F M S", "team_title": "RasenBallsport Leipzig", "npg": "25", "npxG": "21.175246581435204", "xGChain": "35.58640310168266", "xGBuildup": "7.971801660954952"}, {"id": "1236", "player_name": "Patrik Schick", "games": "22", "time": "1313", "goals": "10", "xG": "8.02419900894165", "assists": "2", "xA": "2.9057464860379696", "shots": "53", "key_passes": "20", "yellow_cards": "3", "red_cards": "0", "position": "F S", "team_title": "RasenBallsport Leipzig", "npg": "10", "npxG": "8.02419900894165", "xGChain": "8.005280604586005", "xGBuildup": "1.839195404201746"}, {"id": "5248", "player_name": "Marcel Sabitzer", "games": "32", "time": "2510", "goals": "9", "xG": "6.577641958370805", "assists": "7", "xA": "5.927560870535672", "shots": "70", "key_passes": "60", "yellow_cards": "4", "red_cards": "0", "position": "D F M S", "team_title": "RasenBallsport Leipzig", "npg": "9", "npxG": "6.577641958370805", "xGChain": "19.50988619029522", "xGBuildup": "11.217100314795971"}, {"id": "3300", "player_name": "Christopher Nkunku", "games": "32", "time": "1918", "goals": "5", "xG": "8.3008664380759", "assists": "13", "xA": "9.998640965670347", "shots": "52", "key_passes": "73", "yellow_cards": "2", "red_cards": "0", "position": "D F M S", "team_title": "RasenBallsport Leipzig", "npg": "5", "npxG": "8.3008664380759", "xGChain": "21.607581425458193", "xGBuildup": "8.681431785225868"}, {"id": "5249", "player_name": "Emil Forsberg", "games": "22", "time": "1147", "goals": "5", "xG": "3.511454777792096", "assists": "2", "xA": "2.6887233601883054", "shots": "26", "key_passes": "27", "yellow_cards": "1", "red_cards": "0", "position": "M S", "team_title": "RasenBallsport Leipzig", "npg": "3", "npxG": "1.9959014225751162", "xGChain": "8.254329825751483", "xGBuildup": "4.600940121337771"}, {"id": "5250", "player_name": "Yussuf Poulsen", "games": "22", "time": "1218", "goals": "5", "xG": "6.612248392775655", "assists": "6", "xA": "2.2428674269467592", "shots": "33", "key_passes": "18", "yellow_cards": "2", "red_cards": "0", "position": "F S", "team_title": "RasenBallsport Leipzig", "npg": "5", "npxG": "6.612248392775655", "xGChain": "12.96423082984984", "xGBuildup": "5.633869027718902"}, {"id": "5254", "player_name": "Marcel Halstenberg", "games": "29", "time": "2526", "goals": "3", "xG": "2.4438078170642257", "assists": "3", "xA": "4.261248210445046", "shots": "31", "key_passes": "36", "yellow_cards": "4", "red_cards": "1", "position": "D S", "team_title": "RasenBallsport Leipzig", "npg": "3", "npxG": "2.4438078170642257", "xGChain": "13.555161386728287", "xGBuildup": "11.85619691759348"}, {"id": "5358", "player_name": "Lukas Klostermann", "games": "31", "time": "2655", "goals": "3", "xG": "3.48921306617558", "assists": "1", "xA": "3.3518055705353618", "shots": "12", "key_passes": "16", "yellow_cards": "1", "red_cards": "0", "position": "D M", "team_title": "RasenBallsport Leipzig", "npg": "3", "npxG": "3.48921306617558", "xGChain": "13.82010542601347", "xGBuildup": "10.806204656139016"}, {"id": "5659", "player_name": "Nordi Mukiele", "games": "25", "time": "1795", "goals": "3", "xG": "2.805176912806928", "assists": "1", "xA": "1.5565820168703794", "shots": "22", "key_passes": "14", "yellow_cards": "1", "red_cards": "0", "position": "D M S", "team_title": "RasenBallsport Leipzig", "npg": "3", "npxG": "2.805176912806928", "xGChain": "10.044187754392624", "xGBuildup": "7.228610852733254"}, {"id": "8292", "player_name": "Dani Olmo", "games": "12", "time": "767", "goals": "3", "xG": "1.9231842383742332", "assists": "1", "xA": "1.2144705690443516", "shots": "21", "key_passes": "9", "yellow_cards": "1", "red_cards": "0", "position": "F M S", "team_title": "RasenBallsport Leipzig", "npg": "3", "npxG": "1.9231842383742332", "xGChain": "5.222254779189825", "xGBuildup": "2.7866643965244293"}, {"id": "188", "player_name": "Kevin Kampl", "games": "11", "time": "677", "goals": "2", "xG": "0.28251355048269033", "assists": "2", "xA": "2.7542967200279236", "shots": "5", "key_passes": "10", "yellow_cards": "1", "red_cards": "0", "position": "M S", "team_title": "RasenBallsport Leipzig", "npg": "2", "npxG": "0.28251355048269033", "xGChain": "8.29010347276926", "xGBuildup": "6.8479791432619095"}, {"id": "6109", "player_name": "Konrad Laimer", "games": "29", "time": "2133", "goals": "2", "xG": "0.8008553870022297", "assists": "6", "xA": "2.3724560849368572", "shots": "10", "key_passes": "14", "yellow_cards": "6", "red_cards": "1", "position": "D M S", "team_title": "RasenBallsport Leipzig", "npg": "2", "npxG": "0.8008553870022297", "xGChain": "11.60296574793756", "xGBuildup": "9.921734420582652"}, {"id": "1040", "player_name": "Angelino", "games": "13", "time": "1092", "goals": "1", "xG": "0.8476111367344856", "assists": "2", "xA": "2.4697962533682585", "shots": "5", "key_passes": "20", "yellow_cards": "2", "red_cards": "0", "position": "D M S", "team_title": "RasenBallsport Leipzig", "npg": "1", "npxG": "0.8476111367344856", "xGChain": "6.440510377287865", "xGBuildup": "4.980664670467377"}, {"id": "5257", "player_name": "Willi Orban", "games": "12", "time": "846", "goals": "1", "xG": "0.7313843914307654", "assists": "0", "xA": "0.0729237962514162", "shots": "7", "key_passes": "3", "yellow_cards": "0", "red_cards": "0", "position": "D S", "team_title": "RasenBallsport Leipzig", "npg": "1", "npxG": "0.7313843914307654", "xGChain": "4.842320546507835", "xGBuildup": "4.683449305593967"}, {"id": "7079", "player_name": "Marcelo Saracchi", "games": "4", "time": "173", "goals": "1", "xG": "0.35442282631993294", "assists": "0", "xA": "0.5043646842241287", "shots": "4", "key_passes": "4", "yellow_cards": "1", "red_cards": "0", "position": "D S", "team_title": "RasenBallsport Leipzig", "npg": "1", "npxG": "0.35442282631993294", "xGChain": "1.4328080713748932", "xGBuildup": "0.6309446021914482"}, {"id": "5241", "player_name": "P\u00e9ter Gul\u00e1csi", "games": "32", "time": "2880", "goals": "0", "xG": "0", "assists": "1", "xA": "0.3064655028283596", "shots": "0", "key_passes": "2", "yellow_cards": "0", "red_cards": "0", "position": "GK", "team_title": "RasenBallsport Leipzig", "npg": "0", "npxG": "0", "xGChain": "6.4977756179869175", "xGBuildup": "6.191310111433268"}, {"id": "5243", "player_name": "Dayotchanculle Upamecano", "games": "28", "time": "2360", "goals": "0", "xG": "1.7165028685703874", "assists": "1", "xA": "1.0885728364810348", "shots": "13", "key_passes": "9", "yellow_cards": "6", "red_cards": "1", "position": "D S", "team_title": "RasenBallsport Leipzig", "npg": "0", "npxG": "1.7165028685703874", "xGChain": "10.982741016894579", "xGBuildup": "10.53366944566369"}, {"id": "5246", "player_name": "Diego Demme", "games": "17", "time": "1217", "goals": "0", "xG": "0.7345899101346731", "assists": "0", "xA": "0.7762109711766243", "shots": "4", "key_passes": "11", "yellow_cards": "3", "red_cards": "0", "position": "M S", "team_title": "RasenBallsport Leipzig", "npg": "0", "npxG": "0.7345899101346731", "xGChain": "8.17723761498928", "xGBuildup": "6.776833415031433"}, {"id": "5556", "player_name": "Ademola Lookman", "games": "11", "time": "281", "goals": "0", "xG": "1.1853207293897867", "assists": "0", "xA": "0.9836375545710325", "shots": "11", "key_passes": "7", "yellow_cards": "0", "red_cards": "0", "position": "F S", "team_title": "RasenBallsport Leipzig", "npg": "0", "npxG": "1.1853207293897867", "xGChain": "3.107866544276476", "xGBuildup": "1.0415268503129482"}, {"id": "6110", "player_name": "Yvon Mvogo", "games": "2", "time": "180", "goals": "0", "xG": "0", "assists": "0", "xA": "0", "shots": "0", "key_passes": "0", "yellow_cards": "0", "red_cards": "0", "position": "GK", "team_title": "RasenBallsport Leipzig", "npg": "0", "npxG": "0", "xGChain": "0.6623524129390717", "xGBuildup": "0.6623524129390717"}, {"id": "6326", "player_name": "Ibrahima Konat\u00e9", "games": "8", "time": "562", "goals": "0", "xG": "0.05053295940160751", "assists": "0", "xA": "0.04383406415581703", "shots": "1", "key_passes": "1", "yellow_cards": "2", "red_cards": "0", "position": "D S", "team_title": "RasenBallsport Leipzig", "npg": "0", "npxG": "0.05053295940160751", "xGChain": "4.367094442248344", "xGBuildup": "4.367094442248344"}, {"id": "6369", "player_name": "Ethan Ampadu", "games": "3", "time": "73", "goals": "0", "xG": "0.055435582995414734", "assists": "0", "xA": "0", "shots": "1", "key_passes": "0", "yellow_cards": "0", "red_cards": "0", "position": "S", "team_title": "RasenBallsport Leipzig", "npg": "0", "npxG": "0.055435582995414734", "xGChain": "0.8921722173690796", "xGBuildup": "0.8921722173690796"}, {"id": "7352", "player_name": "Tyler Adams", "games": "14", "time": "955", "goals": "0", "xG": "0.366747859865427", "assists": "0", "xA": "0.6637942809611559", "shots": "7", "key_passes": "7", "yellow_cards": "0", "red_cards": "0", "position": "D M S", "team_title": "RasenBallsport Leipzig", "npg": "0", "npxG": "0.366747859865427", "xGChain": "4.395739451050758", "xGBuildup": "3.720028191804886"}, {"id": "7501", "player_name": "Amadou Haidara", "games": "19", "time": "732", "goals": "0", "xG": "0.7184222899377346", "assists": "1", "xA": "2.0532536022365093", "shots": "19", "key_passes": "11", "yellow_cards": "1", "red_cards": "0", "position": "M S", "team_title": "RasenBallsport Leipzig", "npg": "0", "npxG": "0.7184222899377346", "xGChain": "6.488309647887945", "xGBuildup": "4.932446148246527"}, {"id": "8092", "player_name": "Tom Krau\u00df", "games": "1", "time": "1", "goals": "0", "xG": "0", "assists": "0", "xA": "0", "shots": "0", "key_passes": "0", "yellow_cards": "0", "red_cards": "0", "position": "S", "team_title": "RasenBallsport Leipzig", "npg": "0", "npxG": "0", "xGChain": "0", "xGBuildup": "0"}, {"id": "8171", "player_name": "Hannes Wolf", "games": "5", "time": "45", "goals": "0", "xG": "0", "assists": "0", "xA": "0.018010452389717102", "shots": "0", "key_passes": "1", "yellow_cards": "0", "red_cards": "0", "position": "S", "team_title": "RasenBallsport Leipzig", "npg": "0", "npxG": "0", "xGChain": "0.04240288957953453", "xGBuildup": "0.02439243718981743"}, {"id": "8502", "player_name": "Dennis Borkowski", "games": "1", "time": "5", "goals": "0", "xG": "0", "assists": "0", "xA": "0", "shots": "0", "key_passes": "0", "yellow_cards": "0", "red_cards": "0", "position": "S", "team_title": "RasenBallsport Leipzig", "npg": "0", "npxG": "0", "xGChain": "0", "xGBuildup": "0"}]